elogs/__init__.py
elogs/_version.py
elogs/dynamo.py
elogs/elogs.py
elogs/mep.py
elogs/s3.py
elogs/dashboard/__init__.py
elogs/dashboard/app.py
elogs/dashboard/labels.py
elogs/dashboard/tables.py
elogs/dashboard/static/s2grid.fgb
elogs/dashboard/templates/_layout.html
elogs/dashboard/templates/bak-browse.html
elogs/dashboard/templates/bak-index.html
elogs/dashboard/templates/bak-s2grid-copy.html
elogs/dashboard/templates/browse.html
elogs/dashboard/templates/index.html
elogs/dashboard/templates/leaflet.html
elogs/dashboard/templates/leaflet_s2grid.html
elogs/dashboard/templates/s2grid.html
elogs/dashboard/templates/txt.html
elogs-0.3.0.dist-info/METADATA
elogs-0.3.0.dist-info/WHEEL
elogs-0.3.0.dist-info/entry_points.txt
elogs-0.3.0.dist-info/RECORD
