Metadata-Version: 2.3
Name: elogs
Version: 0.3.0
Summary: Tracking batch processing tasks and logs on a cluster
Author: VITO RS Vegetation team
Classifier: Operating System :: OS Independent
Classifier: Programming Language :: Python :: 3
Requires-Python: >=3.10
Requires-Dist: boto3>=1.37.0
Requires-Dist: flask-session>=0.8
Requires-Dist: flask>=3.1.0
Requires-Dist: geopandas>=1.0.1
Requires-Dist: loguru
Requires-Dist: python-dotenv>=1.0.1
Requires-Dist: tqdm>=4.5
Provides-Extra: image
Requires-Dist: rasterio>=1.4; extra == 'image'
Requires-Dist: scikit-image>=0.25; extra == 'image'
